itemlist/__init__.py
itemlist/itemlist.py
itemlist/utils.py
tests/__init__.py
tests/test_itemlist.py
tests/test_utils.py
itemlist-0.1.5.dist-info/LICENSE
itemlist-0.1.5.dist-info/METADATA
itemlist-0.1.5.dist-info/WHEEL
itemlist-0.1.5.dist-info/entry_points.txt
itemlist-0.1.5.dist-info/top_level.txt
itemlist-0.1.5.dist-info/RECORD
