Metadata-Version: 2.1
Name: itemlist
Version: 0.1.5
Summary: CLI tool for selecting and executing functions.
Home-page: https://github.com/Luftalian/itemlist
Author: Haruki Nakajima
Author-email: your.email@example.com
Classifier: Programming Language :: Python :: 3
Classifier: License :: OSI Approved :: MIT License
Classifier: Operating System :: OS Independent
Requires-Python: >=3.7
License-File: LICENSE
Requires-Dist: Sphinx>=3.2.1
Requires-Dist: sphinx-autodoc-typehints>=1.11.0
